mylib_009/__init__.py
mylib_009-0.1.dist-info/LICENSE.txt
mylib_009-0.1.dist-info/METADATA
mylib_009-0.1.dist-info/WHEEL
mylib_009-0.1.dist-info/top_level.txt
mylib_009-0.1.dist-info/RECORD
